{
  "gitSyncId": "9e0d2cd8-b3a9-407f-83ce-0ac2fc3106ed_ee3ed9c2-a54a-4cc5-ae1f-b22a9a1366d5",
  "id": "JSModule1_JSModule1.myFun2",
  "isPublic": true,
  "pluginId": "js-plugin",
  "pluginType": "JS",
  "unpublishedAction": {
    "actionConfiguration": {
      "encodeParamsToggle": true,
      "jsArguments": [],
      "paginationType": "NONE",
      "timeoutInMillisecond": 10000
    },
    "clientSideExecution": true,
    "collectionId": "JSModule1_JSModule1",
    "confirmBeforeExecute": false,
    "contextType": "MODULE",
    "datasource": {
      "isAutoGenerated": false,
      "name": "UNUSED_DATASOURCE",
      "pluginId": "js-plugin"
    },
    "dynamicBindingPathList": [
      {
        "key": "body"
      }
    ],
    "executeOnLoad": false,
    "fullyQualifiedName": "JSModule1.myFun2",
    "moduleId": "JSModule1",
    "name": "myFun2",
    "userSetOnLoad": false
  }
}